dpycheck/__init__.py
dpycheck/_channel_perms.py
dpycheck/_error_handler.py
dpycheck/_guild_perms.py
dpycheck/_misc.py
dpycheck/_modifiers.py
dpycheck/_role.py
dpycheck/constants.py
dpycheck/exceptions.py
dpycheck/types.py
dpycheck/utils.py
dpycheck/ctx/__init__.py
dpycheck/ctx/_check.py
dpycheck/itx/__init__.py
dpycheck/itx/_check.py
dpy_check-0.0.2.dist-info/LICENSE
dpy_check-0.0.2.dist-info/METADATA
dpy_check-0.0.2.dist-info/WHEEL
dpy_check-0.0.2.dist-info/top_level.txt
dpy_check-0.0.2.dist-info/RECORD
