Metadata-Version: 2.1
Name: dpy-check
Version: 0.0.2
Summary: A system for making more dynamic and complex checks on discord.py commands
Author-email: "Tanner B. Corcoran" <tannerbcorcoran@gmail.com>
Project-URL: Homepage, https://github.com/tanrbobanr/dpy-check
Classifier: Programming Language :: Python :: 3
Classifier: License :: OSI Approved :: MIT License
Classifier: Operating System :: OS Independent
Requires-Python: >=3.11
License-File: LICENSE
Requires-Dist: discord.py (>=2.0.0)
